[
  {
    "id": "group-news-1",
    "type": "news_group",
    "teamKey": "liverpool",
    "createdAt": "2025-09-29T14:00:00.000Z",
    "title": "Liverpool cruise to dominant 3-0 victory over Manchester United at Anfield",
    "aiSummary": "Arne Slot's side delivered a commanding performance with goals from Salah, Mac Allister, and Gakpo as United had no answer at Anfield.",
    "featuredArticleId": "news-1-source-tia",
    "totalSources": 3,
    "articles": [
      {
        "id": "news-1-source-tia",
        "type": "news",
        "teamKey": "liverpool",
        "createdAt": "2025-09-29T14:00:00.000Z",
        "title": "This Is Anfield: Liverpool dismantle United as Salah stars once again",
        "aiSummary": "Match report covering Liverpool's dominant display and Salah's record-breaking goal tally against United.",
        "source": {
          "id": "thisisanfield",
          "name": "This Is Anfield"
        },
        "publishedAt": "2025-09-29T13:55:00.000Z",
        "originalUrl": "https://www.thisisanfield.com/liverpool-united-report"
      },
      {
        "id": "news-1-source-echo",
        "type": "news",
        "teamKey": "liverpool",
        "createdAt": "2025-09-29T13:58:00.000Z",
        "title": "Liverpool Echo: Slot's tactical masterclass ends United's hopes at Anfield",
        "aiSummary": "Analysis of Arne Slot's game plan and how Liverpool exploited United's defensive weaknesses.",
        "source": {
          "id": "liverpoolecho",
          "name": "Liverpool Echo"
        },
        "publishedAt": "2025-09-29T13:50:00.000Z",
        "originalUrl": "https://www.liverpoolecho.co.uk/liverpool-tactical-masterclass"
      },
      {
        "id": "news-1-source-eotk",
        "type": "news",
        "teamKey": "liverpool",
        "createdAt": "2025-09-29T13:50:00.000Z",
        "title": "Empire of the Kop: Player ratings as Liverpool thrash Man United 3-0",
        "aiSummary": "Individual player ratings and standout performances from Liverpool's emphatic North West derby win.",
        "source": {
          "id": "empireofthekop",
          "name": "Empire of the Kop"
        },
        "publishedAt": "2025-09-29T13:45:00.000Z",
        "originalUrl": "https://www.empireofthekop.com/player-ratings-man-united"
      }
    ]
  },
  {
    "id": "group-news-2",
    "type": "news_group",
    "teamKey": "liverpool",
    "createdAt": "2025-09-29T13:30:00.000Z",
    "title": "Liverpool closing in on Bundesliga centre-back for January transfer window",
    "aiSummary": "Liverpool are in advanced talks to sign a highly-rated centre-back from the Bundesliga as they look to bolster their defensive options ahead of the second half of the season.",
    "featuredArticleId": "news-2-source-echo",
    "totalSources": 2,
    "articles": [
      {
        "id": "news-2-source-echo",
        "type": "news",
        "teamKey": "liverpool",
        "createdAt": "2025-09-29T13:30:00.000Z",
        "title": "Liverpool Echo: Reds on verge of completing deal for Bundesliga defender",
        "aiSummary": "Details on Liverpool's negotiations for the centre-back, his profile and what he would bring to the squad.",
        "source": {
          "id": "liverpoolecho",
          "name": "Liverpool Echo"
        },
        "publishedAt": "2025-09-29T13:25:00.000Z",
        "originalUrl": "https://www.liverpoolecho.co.uk/liverpool-bundesliga-defender"
      },
      {
        "id": "news-2-source-aw",
        "type": "news",
        "teamKey": "liverpool",
        "createdAt": "2025-09-29T13:28:00.000Z",
        "title": "Anfield Watch: Liverpool set to land top defensive target in £40m deal",
        "aiSummary": "Breaking transfer news on Liverpool's pursuit, with expected fee and personal terms reportedly agreed.",
        "source": {
          "id": "anfieldwatch",
          "name": "Anfield Watch"
        },
        "publishedAt": "2025-09-29T13:20:00.000Z",
        "originalUrl": "https://anfieldwatch.co.uk/liverpool-defensive-signing"
      }
    ]
  },
  {
    "id": "group-news-3",
    "type": "news_group",
    "teamKey": "liverpool",
    "createdAt": "2025-09-29T13:00:00.000Z",
    "title": "Academy starlet promoted to first-team training after impressive U21 run",
    "aiSummary": "A young forward who has been dazzling in Liverpool's academy setup has been called up to train with the senior squad by Arne Slot.",
    "featuredArticleId": "news-3-source-lfc",
    "totalSources": 2,
    "articles": [
      {
        "id": "news-3-source-lfc",
        "type": "news",
        "teamKey": "liverpool",
        "createdAt": "2025-09-29T13:00:00.000Z",
        "title": "Liverpool FC Official: Academy prospect joins first-team training",
        "aiSummary": "Official club announcement on the young player's promotion to senior training sessions.",
        "source": {
          "id": "liverpoolfc",
          "name": "Liverpool FC Official"
        },
        "publishedAt": "2025-09-29T12:55:00.000Z",
        "originalUrl": "https://www.liverpoolfc.com/news/academy-prospect-first-team"
      },
      {
        "id": "news-3-source-rtk",
        "type": "news",
        "teamKey": "liverpool",
        "createdAt": "2025-09-29T12:58:00.000Z",
        "title": "Rousing The Kop: Who is the academy gem Slot has called up to the first team?",
        "aiSummary": "In-depth profile of the young player, his strengths and expectations for his future at the club.",
        "source": {
          "id": "rousingthekop",
          "name": "Rousing The Kop"
        },
        "publishedAt": "2025-09-29T12:50:00.000Z",
        "originalUrl": "https://www.rousingthekop.com/academy-gem-profile"
      }
    ]
  }
]